[
  {
    "ContainingType": "Crops_Price_Tracker.Controllers.AlertController",
    "Method": "AddAlert",
    "RelativePath": "api/alert/add",
    "HttpMethod": "POST",
    "IsController": true,
    "Order": 0,
    "Parameters": [
      {
        "Name": "dto",
        "Type": "Crops_Price_Tracker.Models.Alerts.AlertCreateDto",
        "IsRequired": true
      }
    ],
    "ReturnTypes": []
  },
  {
    "ContainingType": "Crops_Price_Tracker.Controllers.AlertController",
    "Method": "GetUserAlerts",
    "RelativePath": "api/alert/my/{userId}",
    "HttpMethod": "GET",
    "IsController": true,
    "Order": 0,
    "Parameters": [
      {
        "Name": "userId",
        "Type": "System.String",
        "IsRequired": true
      },
      {
        "Name": "startDate",
        "Type": "System.DateTimeOffset",
        "IsRequired": false
      },
      {
        "Name": "endDate",
        "Type": "System.DateTimeOffset",
        "IsRequired": false
      }
    ],
    "ReturnTypes": []
  },
  {
    "ContainingType": "Crops_Price_Tracker.Controllers.AuthController",
    "Method": "Generate",
    "RelativePath": "api/auth/generate-otp",
    "HttpMethod": "POST",
    "IsController": true,
    "Order": 0,
    "Parameters": [
      {
        "Name": "request",
        "Type": "Crops_Price_Tracker.Models.UserData.GenerateOtpRequest",
        "IsRequired": true
      }
    ],
    "ReturnTypes": []
  },
  {
    "ContainingType": "Crops_Price_Tracker.Controllers.AuthController",
    "Method": "Verify",
    "RelativePath": "api/auth/verify-otp",
    "HttpMethod": "POST",
    "IsController": true,
    "Order": 0,
    "Parameters": [
      {
        "Name": "request",
        "Type": "Crops_Price_Tracker.Models.UserData.VerifyOtpRequest",
        "IsRequired": true
      }
    ],
    "ReturnTypes": []
  },
  {
    "ContainingType": "Crops_Price_Tracker.Controllers.CropController",
    "Method": "Analyze",
    "RelativePath": "api/crop/analyze",
    "HttpMethod": "GET",
    "IsController": true,
    "Order": 0,
    "Parameters": [
      {
        "Name": "cropName",
        "Type": "System.String",
        "IsRequired": false
      },
      {
        "Name": "marketName",
        "Type": "System.String",
        "IsRequired": false
      },
      {
        "Name": "startDate",
        "Type": "System.DateTimeOffset",
        "IsRequired": false
      },
      {
        "Name": "endDate",
        "Type": "System.DateTimeOffset",
        "IsRequired": false
      }
    ],
    "ReturnTypes": []
  },
  {
    "ContainingType": "Crops_Price_Tracker.Controllers.CropController",
    "Method": "History",
    "RelativePath": "api/crop/history",
    "HttpMethod": "GET",
    "IsController": true,
    "Order": 0,
    "Parameters": [
      {
        "Name": "cropName",
        "Type": "System.String",
        "IsRequired": false
      },
      {
        "Name": "startDate",
        "Type": "System.DateTimeOffset",
        "IsRequired": false
      },
      {
        "Name": "endDate",
        "Type": "System.DateTimeOffset",
        "IsRequired": false
      }
    ],
    "ReturnTypes": []
  }
]